{
  "run_at": "2026-07-10T12:06:56.240208+00:00",
  "strategy": "highest_yes",
  "selections": [
    {
      "event_id": "679344",
      "city": "Paris",
      "market_id": "2842378",
      "groupItemTitle": "35\u00b0C",
      "yes_price": 0.565,
      "yes_token_id": "97073873502688582868531842119284046747202934754963515141348953857295783432522",
      "buy_price": 0.59,
      "share_count": 10,
      "neg_risk": true,
      "tick_size": "0.01",
      "order_min_size": 5,
      "strategy": "highest_yes",
      "forecast_temp_f": null,
      "order_price": 0.565,
      "selection_price": 0.565,
      "gamma_yes_price": 0.555,
      "best_bid": 0.56,
      "best_ask": 0.59,
      "clob_buy_price": 0.59,
      "last_trade_price": 0.57,
      "midpoint": 0.565,
      "outcomePrices": [
        0.555,
        0.445
      ],
      "order_status": "live",
      "order_id": "0xa57aa887f284130f7bfc0f08c6ea7ef3100d5532a0ff2caa6ea87adfe55d87c6",
      "dry_run": false,
      "order_type": "GTD",
      "expires_at": "2026-07-10T12:31:52+00:00"
    },
    {
      "event_id": "679354",
      "city": "Munich",
      "market_id": "2842419",
      "groupItemTitle": "29\u00b0C",
      "yes_price": 0.435,
      "yes_token_id": "57437959948405952303299462074355177346100632389048504570681812324328040448302",
      "buy_price": 0.47,
      "share_count": 10,
      "neg_risk": true,
      "tick_size": "0.01",
      "order_min_size": 5,
      "strategy": "highest_yes",
      "forecast_temp_f": null,
      "order_price": 0.435,
      "selection_price": 0.435,
      "gamma_yes_price": 0.475,
      "best_bid": 0.4,
      "best_ask": 0.47,
      "clob_buy_price": 0.47,
      "last_trade_price": 0.59,
      "midpoint": 0.435,
      "outcomePrices": [
        0.475,
        0.525
      ],
      "order_status": "live",
      "order_id": "0x68ce28353bed4f3797a812b746fc897cb8791395c6ce41b7f07b1df94803ae1d",
      "dry_run": false,
      "order_type": "GTD",
      "expires_at": "2026-07-10T12:31:53+00:00"
    },
    {
      "event_id": "679356",
      "city": "Milan",
      "market_id": "2842440",
      "groupItemTitle": "34\u00b0C",
      "yes_price": 0.49,
      "yes_token_id": "40418686716969640128452332784983774305896089670300544782703824402669091277827",
      "buy_price": 0.51,
      "share_count": 10,
      "neg_risk": true,
      "tick_size": "0.01",
      "order_min_size": 5,
      "strategy": "highest_yes",
      "forecast_temp_f": null,
      "order_price": 0.49,
      "selection_price": 0.49,
      "gamma_yes_price": 0.5,
      "best_bid": 0.47,
      "best_ask": 0.51,
      "clob_buy_price": 0.51,
      "last_trade_price": 0.59,
      "midpoint": 0.49,
      "outcomePrices": [
        0.5,
        0.5
      ],
      "order_status": "live",
      "order_id": "0x8c2c19b414fc6dc4cfa268b20b12ef42e0450f658cc285b28cb79efcebbe62d2",
      "dry_run": false,
      "order_type": "GTD",
      "expires_at": "2026-07-10T12:31:54+00:00"
    },
    {
      "event_id": "679361",
      "city": "Amsterdam",
      "market_id": "2842498",
      "groupItemTitle": "26\u00b0C",
      "yes_price": 0.365,
      "yes_token_id": "83074088720839185726810874219645543142964284215441120872519043449349611615725",
      "buy_price": 0.41,
      "share_count": 10,
      "neg_risk": true,
      "tick_size": "0.01",
      "order_min_size": 5,
      "strategy": "highest_yes",
      "forecast_temp_f": null,
      "order_price": 0.365,
      "selection_price": 0.365,
      "gamma_yes_price": 0.39,
      "best_bid": 0.33,
      "best_ask": 0.41,
      "clob_buy_price": 0.41,
      "last_trade_price": 0.41,
      "midpoint": 0.365,
      "outcomePrices": [
        0.39,
        0.61
      ],
      "order_status": "live",
      "order_id": "0x22a57fada3282a91398e51551619408a43bb00b72b605657bf4b414d2265811c",
      "dry_run": false,
      "order_type": "GTD",
      "expires_at": "2026-07-10T12:31:55+00:00"
    }
  ],
  "skipped_bought": [
    {
      "event_id": "679345",
      "city": "Ankara",
      "market_id": "2842389",
      "group_item_title": "29\u00b0C",
      "reason": "yes_price_max",
      "selection_price": 0.795,
      "yes_price_max": 0.6
    },
    {
      "event_id": "679355",
      "city": "Tel Aviv",
      "market_id": "2842428",
      "group_item_title": "31\u00b0C",
      "reason": "yes_price_max",
      "selection_price": 0.9825,
      "yes_price_max": 0.6
    },
    {
      "event_id": "679357",
      "city": "Madrid",
      "market_id": "2842451",
      "group_item_title": "36\u00b0C",
      "reason": "yes_price_max",
      "selection_price": 0.665,
      "yes_price_max": 0.6
    },
    {
      "event_id": "679358",
      "city": "Warsaw",
      "market_id": "2842464",
      "group_item_title": "19\u00b0C",
      "reason": "yes_price_max",
      "selection_price": 0.715,
      "yes_price_max": 0.6
    },
    {
      "event_id": "679360",
      "city": "Istanbul",
      "market_id": "2842489",
      "group_item_title": "26\u00b0C",
      "reason": "yes_price_max",
      "selection_price": 0.825,
      "yes_price_max": 0.6
    },
    {
      "event_id": "679363",
      "city": "Jeddah",
      "market_id": "2842523",
      "group_item_title": "38\u00b0C",
      "reason": "yes_price_max",
      "selection_price": 0.9445,
      "yes_price_max": 0.6
    },
    {
      "event_id": "679364",
      "city": "Cape Town",
      "market_id": "2842533",
      "group_item_title": "18\u00b0C",
      "reason": "yes_price_max",
      "selection_price": 0.945,
      "yes_price_max": 0.6
    },
    {
      "event_id": "679359",
      "city": "Moscow",
      "market_id": "2842477",
      "group_item_title": "27\u00b0C",
      "reason": "has_full_position",
      "held_shares": 10.0,
      "held_market_id": "2842477",
      "held_group_item_title": "27\u00b0C",
      "target_share_count": 10
    },
    {
      "event_id": "679362",
      "city": "Helsinki",
      "market_id": "2842511",
      "group_item_title": "22\u00b0C",
      "reason": "has_full_position",
      "held_shares": 10.0,
      "held_market_id": "2842511",
      "held_group_item_title": "22\u00b0C",
      "target_share_count": 10
    }
  ]
}