{
  "run_at": "2026-07-11T09:35:42.072622+00:00",
  "strategy": "highest_yes",
  "selections": [],
  "skipped_bought": [
    {
      "event_id": "682940",
      "city": "Lucknow",
      "market_id": "2854470",
      "group_item_title": "34\u00b0C",
      "reason": "yes_price_max",
      "selection_price": 0.879,
      "yes_price_max": 0.6
    },
    {
      "event_id": "682966",
      "city": "Karachi",
      "market_id": "2854760",
      "group_item_title": "34\u00b0C",
      "reason": "yes_price_max",
      "selection_price": 0.982,
      "yes_price_max": 0.6
    }
  ]
}